{"nodes": [{"id": "cliprompt_test", "label": "cliPrompt_test.go", "file_type": "code", "source_file": "cli/internal/cliparamsatisfier/inputsrc/cliprompt/cliPrompt_test.go", "source_location": "L1"}], "edges": [{"source": "cliprompt_test", "target": "io", "relation": "imports_from", "confidence": "EXTRACTED", "source_file": "cli/internal/cliparamsatisfier/inputsrc/cliprompt/cliPrompt_test.go", "source_location": "L4", "weight": 1.0}, {"source": "cliprompt_test", "target": "ginkgo", "relation": "imports_from", "confidence": "EXTRACTED", "source_file": "cli/internal/cliparamsatisfier/inputsrc/cliprompt/cliPrompt_test.go", "source_location": "L6", "weight": 1.0}, {"source": "cliprompt_test", "target": "gomega", "relation": "imports_from", "confidence": "EXTRACTED", "source_file": "cli/internal/cliparamsatisfier/inputsrc/cliprompt/cliPrompt_test.go", "source_location": "L7", "weight": 1.0}, {"source": "cliprompt_test", "target": "clicolorer", "relation": "imports_from", "confidence": "EXTRACTED", "source_file": "cli/internal/cliparamsatisfier/inputsrc/cliprompt/cliPrompt_test.go", "source_location": "L8", "weight": 1.0}, {"source": "cliprompt_test", "target": "clioutput", "relation": "imports_from", "confidence": "EXTRACTED", "source_file": "cli/internal/cliparamsatisfier/inputsrc/cliprompt/cliPrompt_test.go", "source_location": "L9", "weight": 1.0}, {"source": "cliprompt_test", "target": "model", "relation": "imports_from", "confidence": "EXTRACTED", "source_file": "cli/internal/cliparamsatisfier/inputsrc/cliprompt/cliPrompt_test.go", "source_location": "L10", "weight": 1.0}]}